mowidgets/__init__.py
mowidgets/_widget.py
mowidgets-0.1.2.dist-info/licenses/LICENSE
mowidgets-0.1.2.dist-info/WHEEL
mowidgets-0.1.2.dist-info/entry_points.txt
mowidgets-0.1.2.dist-info/METADATA
mowidgets-0.1.2.dist-info/RECORD
