Metadata-Version: 2.4
Name: mowidgets
Version: 0.1.2
Summary: Reusable widgets for marimo notebooks
Author: zilto
Author-email: zilto <68975210+zilto@users.noreply.github.com>
License-File: LICENSE
Requires-Dist: marimo>=0.12.1
Requires-Python: >=3.9
Project-URL: Homepage, https://github.com/zilto/mowidgets
Project-URL: Issues, https://github.com/zilto/mowidgets/issues
